br_logs/__init__.py
br_logs/logs.py
br_logs/servers.py
BR_Logs-0.5.0.dist-info/LICENSE
BR_Logs-0.5.0.dist-info/METADATA
BR_Logs-0.5.0.dist-info/WHEEL
BR_Logs-0.5.0.dist-info/top_level.txt
BR_Logs-0.5.0.dist-info/RECORD
