Metadata-Version: 2.1
Name: BR-Logs
Version: 0.5.0
Summary: A wrapper for the BR-Logs API.
Home-page: https://github.com/sak0v/BR-Logs
Author: Amir Sakov
Author-email: volturisalts@gmail.com
Classifier: Programming Language :: Python :: 3
Classifier: License :: OSI Approved :: MIT License
Classifier: Operating System :: OS Independent
Requires-Python: >=3.10
License-File: LICENSE
Requires-Dist: aiohappyeyeballs ==2.4.2
Requires-Dist: aiohttp ==3.9.0
Requires-Dist: aiosignal ==1.3.1
Requires-Dist: attrs ==24.2.0
Requires-Dist: frozenlist ==1.4.1
Requires-Dist: idna ==3.10
Requires-Dist: multidict ==6.1.0
Requires-Dist: yarl ==1.13.0
Requires-Dist: pytz ==2024.2
